[
 {
    "id": "09eafa2f-5b04-4f91-85c9-9c1794f25f73",
    "title": "C# Corner: Mystery Detective Mod for Stardew Valley!",
    "description": "Let's start building a game mod for Stardew Valley!",
    "date": "2020-09-29T12:00:00.000000-07:00",
    "guest": "",
    "length": 2,
    "thumbnail": "",
    "url": "https://www.twitch.tv/VisualStudio",
    "communityLinks": "https://www.github.com/instafluff"
  },
 {
    "id": "d142f159-5dc9-4149-b089-522edf75db89",
    "title": "C# Corner: Mystery Detective Mod for Stardew Valley!",
    "description": "Let's continue working our game mod for Stardew Valley!",
    "date": "2020-10-06T12:00:00.000000-07:00",
    "guest": "",
    "length": 2,
    "thumbnail": "",
    "url": "https://www.twitch.tv/VisualStudio",
    "communityLinks": "https://www.github.com/instafluff"
  },
]
